llq_mcp_demo/__init__.py
llq_mcp_demo-0.1.0.dist-info/METADATA
llq_mcp_demo-0.1.0.dist-info/WHEEL
llq_mcp_demo-0.1.0.dist-info/entry_points.txt
llq_mcp_demo-0.1.0.dist-info/RECORD
