Metadata-Version: 2.4
Name: llq-mcp-demo
Version: 0.1.0
Summary: Add your description here
Author-email: Liu Liqi <1293238163@qq.com>
Requires-Python: >=3.13
Requires-Dist: mcp[cli]>=1.10.1
